icu_sepsis/__init__.py
icu_sepsis/envs/__init__.py
icu_sepsis/envs/sepsis.py
icu_sepsis/envs/assets/admissible_actions.txt
icu_sepsis/envs/assets/dynamics.npz
icu_sepsis/envs/assets/metadata.json
icu_sepsis/envs/assets/readme.txt
icu_sepsis/utils/__init__.py
icu_sepsis/utils/exceptions.py
icu_sepsis/utils/io.py
icu_sepsis/utils/constants/__init__.py
icu_sepsis/utils/constants/inadmissible_action_strategies.py
icu_sepsis/wrappers/__init__.py
icu_sepsis/wrappers/legacy_gym_wrapper.py
icu_sepsis/wrappers/two_d_actions.py
icu_sepsis-2.0.1.dist-info/METADATA
icu_sepsis-2.0.1.dist-info/WHEEL
icu_sepsis-2.0.1.dist-info/licenses/LICENSE.txt
icu_sepsis-2.0.1.dist-info/RECORD
