Metadata-Version: 2.3
Name: icu-sepsis
Version: 2.0.1
Summary: Python implementation of the ICU-Sepsis environment.
Author: Kartik Choudhary, Dhawal Gupta, Philip S. Thomas
Maintainer-email: Kartik Choudhary <kartikchoudh@cs.umass.edu>
License: MIT License
License-File: LICENSE.txt
Keywords: icu,reinforcement-learning,sepsis
Classifier: Development Status :: 4 - Beta
Classifier: Programming Language :: Python
Requires-Python: >=3.10
Requires-Dist: gym>=0.21.0
Requires-Dist: gymnasium>=0.28.1
Requires-Dist: matplotlib>=3.8.2
Requires-Dist: pandas>=2.2.0
Requires-Dist: pyyaml>=6.0.1
Requires-Dist: scikit-learn>=1.4.0
Requires-Dist: scipy>=1.12.0
Requires-Dist: tqdm>=4.65.0
